r7_surcom_api/__init__.py
r7_surcom_api/cli.py
r7_surcom_api/constants.py
r7_surcom_api/extract.py
r7_surcom_api/functions.py
r7_surcom_api/helpers.py
r7_surcom_api/manifest.py
r7_surcom_api/ref_utils.py
r7_surcom_api/requests_wrapper.py
r7_surcom_api/utils.py
r7_surcom_api-0.7.9.dist-info/licenses/LICENSE
r7_surcom_api-0.7.9.dist-info/METADATA
r7_surcom_api-0.7.9.dist-info/WHEEL
r7_surcom_api-0.7.9.dist-info/top_level.txt
r7_surcom_api-0.7.9.dist-info/RECORD
